cogents_core/__init__.py
cogents_core/consts.py
cogents_core/py.typed
cogents_core/agent/__init__.py
cogents_core/agent/base.py
cogents_core/goalith/errors.py
cogents_core/goalith/service.py
cogents_core/goalith/conflict/conflict.py
cogents_core/goalith/conflict/detector.py
cogents_core/goalith/decomposer/__init__.py
cogents_core/goalith/decomposer/base.py
cogents_core/goalith/decomposer/callable_decomposer.py
cogents_core/goalith/decomposer/llm_decomposer.py
cogents_core/goalith/decomposer/prompts.py
cogents_core/goalith/decomposer/simple_decomposer.py
cogents_core/goalith/goalgraph/graph.py
cogents_core/goalith/goalgraph/node.py
cogents_core/goalith/replanner/base.py
cogents_core/goalith/replanner/replanner.py
cogents_core/llm/__init__.py
cogents_core/llm/base.py
cogents_core/llm/litellm.py
cogents_core/llm/llamacpp.py
cogents_core/llm/message.py
cogents_core/llm/ollama.py
cogents_core/llm/openai.py
cogents_core/llm/openrouter.py
cogents_core/llm/prompt.py
cogents_core/memory/__init__.py
cogents_core/memory/base.py
cogents_core/memory/models.py
cogents_core/memory/memu/__init__.py
cogents_core/memory/memu/llm_adapter.py
cogents_core/memory/memu/memory_store.py
cogents_core/memory/memu/config/__init__.py
cogents_core/memory/memu/config/markdown_config.py
cogents_core/memory/memu/config/activity/config.py
cogents_core/memory/memu/config/event/config.py
cogents_core/memory/memu/config/profile/config.py
cogents_core/memory/memu/memory/__init__.py
cogents_core/memory/memu/memory/embeddings.py
cogents_core/memory/memu/memory/file_manager.py
cogents_core/memory/memu/memory/memory_agent.py
cogents_core/memory/memu/memory/recall_agent.py
cogents_core/memory/memu/memory/actions/__init__.py
cogents_core/memory/memu/memory/actions/add_activity_memory.py
cogents_core/memory/memu/memory/actions/base_action.py
cogents_core/memory/memu/memory/actions/cluster_memories.py
cogents_core/memory/memu/memory/actions/generate_suggestions.py
cogents_core-1.0.0.dist-info/licenses/LICENSE
cogents_core-1.0.0.dist-info/METADATA
cogents_core-1.0.0.dist-info/WHEEL
cogents_core-1.0.0.dist-info/top_level.txt
cogents_core-1.0.0.dist-info/RECORD
