Metadata-Version: 2.4
Name: cogents-core
Version: 1.0.0
Summary: Towards a cognitive agentic framework
Author-email: Xiaming Chen <chenxm35@gmail.com>
Maintainer-email: Xiaming Chen <chenxm35@gmail.com>
License-Expression: MIT
Project-URL: Homepage, https://github.com/caesar0301/cogents-core
Project-URL: Repository, https://github.com/caesar0301/cogents-core
Keywords: agents,multi-agent system,cognition,artificial intelligence
Classifier: Development Status :: 4 - Beta
Classifier: Intended Audience :: Developers
Classifier: Operating System :: OS Independent
Classifier: Programming Language :: Python :: 3
Classifier: Programming Language :: Python :: 3.11
Classifier: Programming Language :: Python :: 3.12
Classifier: Topic :: Software Development :: Libraries :: Python Modules
Requires-Python: >=3.11
License-File: LICENSE
Requires-Dist: pydantic>=2.0.0
Requires-Dist: requests>=2.31.0
Requires-Dist: python-dotenv>=1.1.1
Requires-Dist: colorlog>=6.8.0
Requires-Dist: typing-extensions>=4.8.0
Requires-Dist: deprecated>=1.2.18
Requires-Dist: bubus>=1.5.6
Requires-Dist: openai>=1.0.0
Requires-Dist: instructor>=1.10.0
Requires-Dist: google-genai>=1.5.0
Requires-Dist: litellm>=1.0.0
Requires-Dist: ollama>=0.5.3
Requires-Dist: huggingface-hub>=0.34.4
Requires-Dist: llama-cpp-python>=0.3.16
Requires-Dist: langchain-core>=0.3.72
Requires-Dist: langchain-text-splitters>=0.3.0
Requires-Dist: langchain-ollama>=0.2.0
Requires-Dist: langgraph>=0.5.4
Requires-Dist: networkx>=3.5
Requires-Dist: mcp>=1.0.0
Requires-Dist: protobuf<6,>=5
Requires-Dist: weaviate-client<5,>=4
Requires-Dist: psycopg2>=2.9.10
Requires-Dist: psycopg2-binary>=2.9.0
Provides-Extra: dev
Requires-Dist: pytest<9,>=8.2; extra == "dev"
Requires-Dist: pytest-cov>=4.0.0; extra == "dev"
Requires-Dist: pytest-asyncio>=1.1.0; extra == "dev"
Requires-Dist: pytest-tornasync>=0.6.0.post2; extra == "dev"
Requires-Dist: pytest-trio>=0.8.0; extra == "dev"
Requires-Dist: pytest-twisted>=1.14.3; extra == "dev"
Requires-Dist: twisted>=25.5.0; extra == "dev"
Requires-Dist: black>=23.0.0; extra == "dev"
Requires-Dist: isort>=5.12.0; extra == "dev"
Requires-Dist: flake8>=7.3.0; extra == "dev"
Requires-Dist: autoflake>=2.3.1; extra == "dev"
Requires-Dist: pillow>=11.3.0; extra == "dev"
Dynamic: license-file
